pystrategy_test_py/__init__.py
pystrategy_test_py/resta_function.py
pystrategy_test_py/sum_function.py
pystrategy_test_py-1.0.16.dist-info/METADATA
pystrategy_test_py-1.0.16.dist-info/WHEEL
pystrategy_test_py-1.0.16.dist-info/top_level.txt
pystrategy_test_py-1.0.16.dist-info/RECORD
