Metadata-Version: 2.1
Name: pystrategy-test-py
Version: 1.0.16
Summary: This a test for the pyStrategy function.  This information will be updated. 
Home-page: https://github.com/faprieto96/pystrategy_test_py
Author: Francisco A. Prieto Rodriguez, Francisco de Asís Fernández Navarro, David Becerra Alonso
License: UNKNOWN
Platform: UNKNOWN
Classifier: Programming Language :: Python :: 3
Classifier: License :: OSI Approved :: MIT License
Classifier: Operating System :: OS Independent
Requires-Python: >=3.0
